{"nodes": [{"id": "public_shield_dashboard_shield_logo", "label": "Dashboard Shield SVG Logo", "file_type": "image", "source_file": "dashboard/public/shield.svg", "source_location": null, "source_url": null, "captured_at": null, "author": null, "contributor": null}], "edges": [{"source": "public_shield_dashboard_shield_logo", "target": "nsc2026_02_full_report_react_dashboard", "relation": "conceptually_related_to", "confidence": "INFERRED", "confidence_score": 0.95, "source_file": "dashboard/public/shield.svg", "source_location": null, "weight": 0.95}], "hyperedges": []}