{"nodes": [{"id": "home_user_security_backend_app_routers_history_py", "label": "history.py", "file_type": "code", "source_file": "/home/user/Security/backend/app/routers/history.py", "source_location": "L1"}, {"id": "routers_history_history", "label": "history()", "file_type": "code", "source_file": "/home/user/Security/backend/app/routers/history.py", "source_location": "L24"}, {"id": "int", "label": "int", "file_type": "code", "source_file": "/home/user/Security/backend/app/routers/history.py", "source_location": "L24"}, {"id": "str", "label": "str", "file_type": "code", "source_file": "/home/user/Security/backend/app/routers/history.py", "source_location": "L24"}, {"id": "datetime", "label": "datetime", "file_type": "code", "source_file": "/home/user/Security/backend/app/routers/history.py", "source_location": "L24"}, {"id": "asyncsession", "label": "AsyncSession", "file_type": "code", "source_file": "/home/user/Security/backend/app/routers/history.py", "source_location": "L24"}, {"id": "historyresponse", "label": "HistoryResponse", "file_type": "code", "source_file": "/home/user/Security/backend/app/routers/history.py", "source_location": "L24"}, {"id": "routers_history_rationale_1", "label": "GET /api/v1/history -- paginated, filterable check history.", "file_type": "rationale", "source_file": "/home/user/Security/backend/app/routers/history.py", "source_location": "L1"}], "edges": [{"source": "home_user_security_backend_app_routers_history_py", "target": "datetime", "relation": "imports", "context": "import", "confidence": "EXTRACTED", "source_file": "/home/user/Security/backend/app/routers/history.py", "source_location": "L5", "weight": 1.0}, {"source": "home_user_security_backend_app_routers_history_py", "target": "fastapi", "relation": "imports_from", "context": "import", "confidence": "EXTRACTED", "source_file": "/home/user/Security/backend/app/routers/history.py", "source_location": "L7", "weight": 1.0}, {"source": "home_user_security_backend_app_routers_history_py", "target": "sqlalchemy_ext_asyncio", "relation": "imports_from", "context": "import", "confidence": "EXTRACTED", "source_file": "/home/user/Security/backend/app/routers/history.py", "source_location": "L8", "weight": 1.0}, {"source": "home_user_security_backend_app_routers_history_py", "target": "app_crud", "relation": "imports_from", "context": "import", "confidence": "EXTRACTED", "source_file": "/home/user/Security/backend/app/routers/history.py", "source_location": "L10", "weight": 1.0}, {"source": "home_user_security_backend_app_routers_history_py", "target": "app_database", "relation": "imports_from", "context": "import", "confidence": "EXTRACTED", "source_file": "/home/user/Security/backend/app/routers/history.py", "source_location": "L11", "weight": 1.0}, {"source": "home_user_security_backend_app_routers_history_py", "target": "app_deps", "relation": "imports_from", "context": "import", "confidence": "EXTRACTED", "source_file": "/home/user/Security/backend/app/routers/history.py", "source_location": "L12", "weight": 1.0}, {"source": "home_user_security_backend_app_routers_history_py", "target": "app_schemas", "relation": "imports_from", "context": "import", "confidence": "EXTRACTED", "source_file": "/home/user/Security/backend/app/routers/history.py", "source_location": "L13", "weight": 1.0}, {"source": "home_user_security_backend_app_routers_history_py", "target": "routers_history_history", "relation": "contains", "confidence": "EXTRACTED", "source_file": "/home/user/Security/backend/app/routers/history.py", "source_location": "L24", "weight": 1.0}, {"source": "routers_history_history", "target": "int", "relation": "references", "context": "parameter_type", "confidence": "EXTRACTED", "source_file": "/home/user/Security/backend/app/routers/history.py", "source_location": "L24", "weight": 1.0}, {"source": "routers_history_history", "target": "int", "relation": "references", "context": "parameter_type", "confidence": "EXTRACTED", "source_file": "/home/user/Security/backend/app/routers/history.py", "source_location": "L24", "weight": 1.0}, {"source": "routers_history_history", "target": "str", "relation": "references", "context": "parameter_type", "confidence": "EXTRACTED", "source_file": "/home/user/Security/backend/app/routers/history.py", "source_location": "L24", "weight": 1.0}, {"source": "routers_history_history", "target": "str", "relation": "references", "context": "parameter_type", "confidence": "EXTRACTED", "source_file": "/home/user/Security/backend/app/routers/history.py", "source_location": "L24", "weight": 1.0}, {"source": "routers_history_history", "target": "datetime", "relation": "references", "context": "parameter_type", "confidence": "EXTRACTED", "source_file": "/home/user/Security/backend/app/routers/history.py", "source_location": "L24", "weight": 1.0}, {"source": "routers_history_history", "target": "datetime", "relation": "references", "context": "parameter_type", "confidence": "EXTRACTED", "source_file": "/home/user/Security/backend/app/routers/history.py", "source_location": "L24", "weight": 1.0}, {"source": "routers_history_history", "target": "asyncsession", "relation": "references", "context": "parameter_type", "confidence": "EXTRACTED", "source_file": "/home/user/Security/backend/app/routers/history.py", "source_location": "L24", "weight": 1.0}, {"source": "routers_history_history", "target": "historyresponse", "relation": "references", "context": "return_type", "confidence": "EXTRACTED", "source_file": "/home/user/Security/backend/app/routers/history.py", "source_location": "L24", "weight": 1.0}, {"source": "routers_history_history", "target": "historyresponse", "relation": "calls", "context": "call", "confidence": "EXTRACTED", "source_file": "/home/user/Security/backend/app/routers/history.py", "source_location": "L56", "weight": 1.0}, {"source": "routers_history_rationale_1", "target": "home_user_security_backend_app_routers_history_py", "relation": "rationale_for", "confidence": "EXTRACTED", "source_file": "/home/user/Security/backend/app/routers/history.py", "source_location": "L1", "weight": 1.0}], "raw_calls": [{"caller_nid": "routers_history_history", "callee": "get_history", "is_member_call": false, "source_file": "/home/user/Security/backend/app/routers/history.py", "source_location": "L33"}, {"caller_nid": "routers_history_history", "callee": "HistoryItem", "is_member_call": false, "source_file": "/home/user/Security/backend/app/routers/history.py", "source_location": "L43"}, {"caller_nid": "routers_history_history", "callee": "isoformat", "is_member_call": true, "source_file": "/home/user/Security/backend/app/routers/history.py", "source_location": "L51"}]}